subtitle_analyzer/__init__.py
subtitle_analyzer/empty.srt
subtitle_analyzer/entry.py
subtitle_analyzer/lib.py
subtitle_analyzer/phrase_analyzer.py
subtitle_analyzer/phrase_ass_writer.py
subtitle_analyzer/tbr.py
subtitle_analyzer/vocab_analyzer.py
subtitle_analyzer/vocab_ass_writer.py
subtitle_analyzer-0.1.23.dist-info/METADATA
subtitle_analyzer-0.1.23.dist-info/WHEEL
subtitle_analyzer-0.1.23.dist-info/entry_points.txt
subtitle_analyzer-0.1.23.dist-info/RECORD
